{
  "namespace": {
    "": 0,
    "نقاش": 1,
    "TALK": 1,
    "مستخدم": 2,
    "USER": 2,
    "نقاش المستخدم": 3,
    "USER TALK": 3,
    "ويكيبيديا": 4,
    "PROJECT": 4,
    "نقاش ويكيبيديا": 5,
    "PROJECT TALK": 5,
    "ملف": 6,
    "FILE": 6,
    "نقاش الملف": 7,
    "FILE TALK": 7,
    "ميدياويكي": 8,
    "MEDIAWIKI": 8,
    "نقاش ميدياويكي": 9,
    "MEDIAWIKI TALK": 9,
    "قالب": 10,
    "TEMPLATE": 10,
    "نقاش القالب": 11,
    "TEMPLATE TALK": 11,
    "مساعدة": 12,
    "HELP": 12,
    "نقاش المساعدة": 13,
    "HELP TALK": 13,
    "تصنيف": 14,
    "CATEGORY": 14,
    "نقاش التصنيف": 15,
    "CATEGORY TALK": 15,
    "بوابة": 100,
    "نقاش البوابة": 101,
    "وحدة": 828,
    "MODULE": 828,
    "نقاش الوحدة": 829,
    "MODULE TALK": 829,
    "إضافة": 2300,
    "GADGET": 2300,
    "نقاش الإضافة": 2301,
    "GADGET TALK": 2301,
    "تعريف الإضافة": 2302,
    "GADGET DEFINITION": 2302,
    "نقاش تعريف الإضافة": 2303,
    "GADGET DEFINITION TALK": 2303,
    "موضوع": 2600,
    "TOPIC": 2600,
    "ميديا": -2,
    "MEDIA": -2,
    "خاص": -1,
    "SPECIAL": -1,
    "وسائط": -2,
    "مستخدمة": 2,
    "نقاش المستخدمة": 3,
    "WIKIPEDIA": 4,
    "وب": 4,
    "WIKIPEDIA TALK": 5,
    "نو": 5,
    "IMAGE": 6,
    "صورة": 6,
    "IMAGE TALK": 7,
    "نقاش الصورة": 7
  },
  "mainpage": "الصفحة الرئيسية"
}