{
  "namespace": {
    "": 0,
    "DISCUSSIÓ": 1,
    "TALK": 1,
    "USUARI": 2,
    "USER": 2,
    "USUARI DISCUSSIÓ": 3,
    "USER TALK": 3,
    "VIQUIPÈDIA": 4,
    "PROJECT": 4,
    "VIQUIPÈDIA DISCUSSIÓ": 5,
    "PROJECT TALK": 5,
    "FITXER": 6,
    "FILE": 6,
    "FITXER DISCUSSIÓ": 7,
    "FILE TALK": 7,
    "MEDIAWIKI": 8,
    "MEDIAWIKI DISCUSSIÓ": 9,
    "MEDIAWIKI TALK": 9,
    "PLANTILLA": 10,
    "TEMPLATE": 10,
    "PLANTILLA DISCUSSIÓ": 11,
    "TEMPLATE TALK": 11,
    "AJUDA": 12,
    "HELP": 12,
    "AJUDA DISCUSSIÓ": 13,
    "HELP TALK": 13,
    "CATEGORIA": 14,
    "CATEGORY": 14,
    "CATEGORIA DISCUSSIÓ": 15,
    "CATEGORY TALK": 15,
    "PORTAL": 100,
    "PORTAL DISCUSSIÓ": 101,
    "VIQUIPROJECTE": 102,
    "VIQUIPROJECTE DISCUSSIÓ": 103,
    "MÒDUL": 828,
    "MODULE": 828,
    "MÒDUL DISCUSSIÓ": 829,
    "MODULE TALK": 829,
    "GADGET": 2300,
    "GADGET TALK": 2301,
    "GADGET DEFINITION": 2302,
    "GADGET DEFINITION TALK": 2303,
    "TEMA": 2600,
    "TOPIC": 2600,
    "MEDIA": -2,
    "ESPECIAL": -1,
    "SPECIAL": -1,
    "USUÀRIA": 2,
    "UTILISATOR": 2,
    "DISCUSSION UTILISATOR": 3,
    "DISCUTIDA UTILISATOR": 3,
    "USUÀRIA DISCUSSIÓ": 3,
    "WIKIPEDIA": 4,
    "WIKIPEDIA TALK": 5,
    "IMAGE": 6,
    "IMATGE": 6,
    "DISCUSSION IMATGE": 7,
    "DISCUTIDA IMATGE": 7,
    "IMAGE TALK": 7,
    "IMATGE DISCUSSIÓ": 7,
    "MEDIAÒIQUI": 8,
    "DISCUSSION MEDIAÒIQUI": 9,
    "DISCUTIDA MEDIAÒIQUI": 9,
    "DISCUTIDA MODÈL": 11,
    "DISCUTIDA AJUDA": 13,
    "DISCUTIDA CATEGORIA": 15
  },
  "mainpage": "PORTADA"
}