{"namespace":{"":0,"MÓDULO DISCUSIÓN":829,"HELP":12,"MODULE":828,"ARCHIVO":6,"CATEGORY":14,"PROJECT TALK":5,"FILE TALK":7,"ARCHIVO DISCUSIÓN":7,"EDUCATION PROGRAM":446,"AYUDA":12,"WIKIPEDIA DISCUSIÓN":5,"WIKIPEDIA":4,"PLANTILLA DISCUSIÓN":11,"GADGET":2300,"HELP TALK":13,"FILE":6,"MÓDULO":828,"USER TALK":3,"TEMPLATE":10,"ESPECIAL":-1,"EDUCATION PROGRAM TALK":447,"GADGET TALK":2301,"PORTAL DISCUSIÓN":101,"MEDIAWIKI DISCUSIÓN":9,"USUARIO":2,"MEDIA":-2,"ACCESORIO DEFINICIÓN DISCUSIÓN":2303,"WIKIPROYECTO":102,"GADGET DEFINITION":2302,"MEDIAWIKI TALK":9,"ACCESORIO DEFINICIÓN":2302,"GADGET DEFINITION TALK":2303,"TEMPLATE TALK":11,"USUARIO DISCUSIÓN":3,"USER":2,"TALK":1,"PROJECT":4,"ACCESORIO":2300,"WIKIPROYECTO DISCUSIÓN":103,"PLANTILLA":10,"DISCUSIÓN":1,"AYUDA DISCUSIÓN":13,"MEDIAWIKI":8,"CATEGORÍA":14,"CATEGORÍA DISCUSIÓN":15,"SPECIAL":-1,"ACCESORIO DISCUSIÓN":2301,"MODULE TALK":829,"CATEGORY TALK":15,"MEDIO":-2,"PORTAL":100},"mainpage":"WIKIPEDIA:PORTADA"}