{
  "namespace": {
    "": 0,
    "DISCUSSION": 1,
    "TALK": 1,
    "UTILISATOR": 2,
    "USER": 2,
    "DISCUSSION UTILISATOR": 3,
    "USER TALK": 3,
    "VOUIQUIPÈDIA": 4,
    "PROJECT": 4,
    "DISCUSSION VOUIQUIPÈDIA": 5,
    "PROJECT TALK": 5,
    "FICHIÉR": 6,
    "FILE": 6,
    "DISCUSSION FICHIÉR": 7,
    "FILE TALK": 7,
    "MEDIAWIKI": 8,
    "DISCUSSION MEDIAWIKI": 9,
    "MEDIAWIKI TALK": 9,
    "MODÈLO": 10,
    "TEMPLATE": 10,
    "DISCUSSION MODÈLO": 11,
    "TEMPLATE TALK": 11,
    "ÉDE": 12,
    "HELP": 12,
    "DISCUSSION ÉDE": 13,
    "HELP TALK": 13,
    "CATÈGORIE": 14,
    "CATEGORY": 14,
    "DISCUSSION CATÈGORIE": 15,
    "CATEGORY TALK": 15,
    "MODULE": 828,
    "DISCUSSION MODULE": 829,
    "MODULE TALK": 829,
    "GADGET": 2300,
    "DISCUSSION GADGET": 2301,
    "GADGET TALK": 2301,
    "DÉFINITION DE GADGET": 2302,
    "GADGET DEFINITION": 2302,
    "DISCUSSION DÉFINITION DE GADGET": 2303,
    "GADGET DEFINITION TALK": 2303,
    "MÈDIA": -2,
    "MEDIA": -2,
    "SPÈCIÂL": -1,
    "SPECIAL": -1,
    "DISCUTAR": 1,
    "DISCUTER": 1,
    "USANCIÉR": 2,
    "DISCUSSION UTILISATEUR": 3,
    "DISCUSSION USANCIÉR": 3,
    "WIKIPEDIA": 4,
    "WIKIPEDIA TALK": 5,
    "IMAGE": 6,
    "ÉMÂGE": 6,
    "DISCUSSION FICHIER": 7,
    "DISCUSSION IMAGE": 7,
    "DISCUSSION ÉMÂGE": 7,
    "IMAGE TALK": 7,
    "DISCUSSION MODÈLE": 11,
    "DISCUSSION AIDE": 13,
    "DISCUSSION CATÉGORIE": 15
  },
  "mainpage": "VOUIQUIPÈDIA:REÇUA PRINCIPÂLA"
}