{
  "mainpage" : "BABBAN SHAFI",
  "namespace" : {
    "" : 0,
    "CATEGORY" : 14,
    "CATEGORY TALK" : 15,
    "FAYIL" : 6,
    "FILE" : 6,
    "FILE TALK" : 7,
    "HELP" : 12,
    "HELP TALK" : 13,
    "IMAGE" : 6,
    "IMAGE TALK" : 7,
    "MEDIA" : -2,
    "MEDIAWIKI" : 8,
    "MEDIAWIKI TALK" : 9,
    "MIDIYA" : -2,
    "MODULE" : 828,
    "MODULE TALK" : 829,
    "MUSAMMAN" : -1,
    "PROJECT" : 4,
    "PROJECT TALK" : 5,
    "RUKUNI" : 14,
    "SAMFURI" : 10,
    "SPECIAL" : -1,
    "TAIMAKO" : 12,
    "TALK" : 1,
    "TATTAUNAWA" : 1,
    "TATTAUNAWAR FAYIL" : 7,
    "TATTAUNAWAR MEDIAWIKI" : 9,
    "TATTAUNAWAR RUKUNI" : 15,
    "TATTAUNAWAR SAMFURI" : 11,
    "TATTAUNAWAR TAIMAKO" : 13,
    "TATTAUNAWAR USER" : 3,
    "TATTAUNAWAR WIKIPEDIA" : 5,
    "TEMPLATE" : 10,
    "TEMPLATE TALK" : 11,
    "TIMEDTEXT" : 710,
    "TIMEDTEXT TALK" : 711,
    "USER" : 2,
    "USER TALK" : 3,
    "WIKIPEDIA" : 4,
    "WIKIPEDIA TALK" : 5,
    "WP" : 4
  }
}