{
  "mainpage" : "मू पौ",
  "namespace" : {
    "" : 0,
    "CATEGORY" : 14,
    "CATEGORY TALK" : 15,
    "FILE" : 6,
    "FILE TALK" : 7,
    "GADGET" : 2300,
    "GADGET DEFINITION" : 2302,
    "GADGET DEFINITION TALK" : 2303,
    "GADGET TALK" : 2301,
    "HELP" : 12,
    "HELP TALK" : 13,
    "IMAGE" : 6,
    "IMAGE TALK" : 7,
    "MEDIA" : -2,
    "MEDIAWIKI" : 8,
    "MEDIAWIKI TALK" : 9,
    "MODULE" : 828,
    "MODULE TALK" : 829,
    "PROJECT" : 4,
    "PROJECT TALK" : 5,
    "SPECIAL" : -1,
    "TALK" : 1,
    "TEMPLATE" : 10,
    "TEMPLATE TALK" : 11,
    "USER" : 2,
    "USER TALK" : 3,
    "WIKIPEDIA" : 4,
    "WIKIPEDIA TALK" : 5,
    "किपा" : 6,
    "किपा खँलाबँला" : 7,
    "खँलाबँला" : 1,
    "ग्वाहालि" : 12,
    "ग्वाहालि खँलाबँला" : 13,
    "छ्येलेमि" : 2,
    "छ्येलेमि खँलाबँला" : 3,
    "दबू" : 100,
    "दबू खँलाबँला" : 101,
    "पुचः" : 14,
    "पुचः खँलाबँला" : 15,
    "माध्यम" : -2,
    "मिडियाविकि" : 8,
    "मिडियाविकि खँलाबँला" : 9,
    "विकिपिडिया" : 4,
    "विकिपिडिया खँलाबँला" : 5,
    "विशेष" : -1
  }
}