{
  "namespace": {
    "": 0,
    "PAGIN": 1,
    "TALK": 1,
    "KÄYTTÄI": 2,
    "USER": 2,
    "KÄYTTÄI PAGIN": 3,
    "USER TALK": 3,
    "WIKIPEDII": 4,
    "PROJECT": 4,
    "WIKIPEDIEN PAGINAT": 5,
    "PROJECT TALK": 5,
    "FAILU": 6,
    "FILE": 6,
    "FAILU PAGIN": 7,
    "FILE TALK": 7,
    "MEDIIWIKI": 8,
    "MEDIAWIKI": 8,
    "MEDIIWIKI PAGIN": 9,
    "MEDIAWIKI TALK": 9,
    "ŠABLONU": 10,
    "TEMPLATE": 10,
    "ŠABLONU PAGIN": 11,
    "TEMPLATE TALK": 11,
    "ABU": 12,
    "HELP": 12,
    "ABU PAGIN": 13,
    "HELP TALK": 13,
    "KATEGOURII": 14,
    "CATEGORY": 14,
    "KATEGOURII PAGIN": 15,
    "CATEGORY TALK": 15,
    "MODUULI": 828,
    "MODULE": 828,
    "KESKUSTELU MODUULISTA": 829,
    "MODULE TALK": 829,
    "PIENOISOHJELMA": 2300,
    "GADGET": 2300,
    "KESKUSTELU PIENOISOHJELMASTA": 2301,
    "GADGET TALK": 2301,
    "PIENOISOHJELMAN MÄÄRITYS": 2302,
    "GADGET DEFINITION": 2302,
    "KESKUSTELU PIENOISOHJELMAN MÄÄRITYKSESTÄ": 2303,
    "GADGET DEFINITION TALK": 2303,
    "MEDII": -2,
    "MEDIA": -2,
    "ERIKOINE": -1,
    "SPECIAL": -1,
    "WIKIPEDIA": 4,
    "WIKIPEDIA TALK": 5,
    "IMAGE": 6,
    "KUVA": 6,
    "IMAGE TALK": 7,
    "KESKUSTELU KUVASTA": 7
  },
  "mainpage": "PIÄSIVU"
}