{
  "mainpage" : "ГОЛОВНА СТОРІНКА",
  "namespace" : {
    "" : 0,
    "CATEGORY" : 14,
    "CATEGORY TALK" : 15,
    "EDUCATION PROGRAM" : 446,
    "EDUCATION PROGRAM TALK" : 447,
    "FILE" : 6,
    "FILE TALK" : 7,
    "GADGET" : 2300,
    "GADGET DEFINITION" : 2302,
    "GADGET DEFINITION TALK" : 2303,
    "GADGET TALK" : 2301,
    "HELP" : 12,
    "HELP TALK" : 13,
    "MEDIA" : -2,
    "MEDIAWIKI" : 8,
    "MEDIAWIKI TALK" : 9,
    "MODULE" : 828,
    "MODULE TALK" : 829,
    "PROJECT" : 4,
    "PROJECT TALK" : 5,
    "SPECIAL" : -1,
    "TALK" : 1,
    "TEMPLATE" : 10,
    "TEMPLATE TALK" : 11,
    "USER" : 2,
    "USER TALK" : 3,
    "ВІКІПЕДІЯ" : 4,
    "ДОВІДКА" : 12,
    "КАТЕГОРІЯ" : 14,
    "КОРИСТУВАЧ" : 2,
    "МЕДІА" : -2,
    "МОДУЛЬ" : 828,
    "ОБГОВОРЕННЯ" : 1,
    "ОБГОВОРЕННЯ MEDIAWIKI" : 9,
    "ОБГОВОРЕННЯ ВІКІПЕДІЇ" : 5,
    "ОБГОВОРЕННЯ ДОВІДКИ" : 13,
    "ОБГОВОРЕННЯ КАТЕГОРІЇ" : 15,
    "ОБГОВОРЕННЯ КОРИСТУВАЧА" : 3,
    "ОБГОВОРЕННЯ МОДУЛЯ" : 829,
    "ОБГОВОРЕННЯ ПОРТАЛУ" : 101,
    "ОБГОВОРЕННЯ ФАЙЛУ" : 7,
    "ОБГОВОРЕННЯ ШАБЛОНУ" : 11,
    "ПОРТАЛ" : 100,
    "СПЕЦІАЛЬНА" : -1,
    "ФАЙЛ" : 6,
    "ШАБЛОН" : 10
  }
}