{
  "mainpage" : "THÂU-IA̍H",
  "namespace" : {
    "" : 0,
    "CATEGORY" : 14,
    "CATEGORY TALK" : 15,
    "FILE" : 6,
    "FILE TALK" : 7,
    "GADGET" : 2300,
    "GADGET DEFINITION" : 2302,
    "GADGET DEFINITION TALK" : 2303,
    "GADGET TALK" : 2301,
    "HELP" : 12,
    "HELP TALK" : 13,
    "IŌNG-CHIÁ" : 2,
    "IŌNG-CHIÁ THÓ-LŪN" : 3,
    "LŪI-PIA̍T" : 14,
    "LŪI-PIA̍T THÓ-LŪN" : 15,
    "MEDIA" : -2,
    "MEDIAWIKI" : 8,
    "MEDIAWIKI TALK" : 9,
    "MEDIAWIKI THÓ-LŪN" : 9,
    "MODULE" : 828,
    "MODULE TALK" : 829,
    "MÛI-THÉ" : -2,
    "PANG-BÔ͘" : 10,
    "PANG-BÔ͘ THÓ-LŪN" : 11,
    "PANG-CHĀN" : 12,
    "PANG-CHĀN THÓ-LŪN" : 13,
    "PORTAL" : 100,
    "PORTAL TALK" : 101,
    "PROJECT" : 4,
    "PROJECT TALK" : 5,
    "SPECIAL" : -1,
    "TALK" : 1,
    "TEK-PIA̍T" : -1,
    "TEMPLATE" : 10,
    "TEMPLATE TALK" : 11,
    "THÓ-LŪN" : 1,
    "TÓNG-ÀN" : 6,
    "TÓNG-ÀN THÓ-LŪN" : 7,
    "USER" : 2,
    "USER TALK" : 3,
    "WIKIPEDIA" : 4,
    "WIKIPEDIA THÓ-LŪN" : 5,
    "模組" : 828,
    "模組討論" : 829
  }
}